lathorp/__init__.py
lathorp/fixtures.py
lathorp-0.2.0.dist-info/LICENSE
lathorp-0.2.0.dist-info/METADATA
lathorp-0.2.0.dist-info/WHEEL
lathorp-0.2.0.dist-info/top_level.txt
lathorp-0.2.0.dist-info/RECORD
