Metadata-Version: 2.1
Name: lathorp
Version: 0.2.0
Summary: pytest fixtures for PostgreSQL
Home-page: https://github.com/eladkehat/lathorp
Author: Elad Kehat
Author-email: eladkehat@gmail.com
License: MIT
Keywords: pytest postgresql pgsql testing
Platform: UNKNOWN
Classifier: Development Status :: 3 - Alpha
Classifier: Intended Audience :: Developers
Classifier: License :: OSI Approved :: MIT License
Classifier: Operating System :: OS Independent
Classifier: Programming Language :: Python :: 3.7
Classifier: Topic :: Database
Classifier: Topic :: Software Development :: Testing
Classifier: Typing :: Typed
Requires-Python: >=3.7
Requires-Dist: psycopg2-binary (>=2.7)
Requires-Dist: pytest (>=4.3)
Requires-Dist: testing.postgresql (>=1.3)
